{
  "artifact": "phase5_5_trial_checkpoint_v1",
  "batch_id": "P5BAT-P5-DV-1.0.2-A7C91E42-phase5_adversarial_core-M4-MIX-MIX-BASELINE-A31E6ADD-8FA4",
  "checkpoint_sequence": 97,
  "completed_lineage_count": 542,
  "last_attempt_id": "P5ATT-T04914-A000-A31E6ADD",
  "last_target_trial_id": "T04914",
  "lineage_sha256": "888545840b068b81f47d96b0ab5a226a1e8451e6bb3aafb276cb2199e6e6f526",
  "model_slot": "M4",
  "parent_head": "19732c371034cc0fe6a8629b8f9ec3794a5317e9",
  "run_id": "P5RUN-P5-DV-1.0.2-A7C91E42-M4-20260718-E19BD69F",
  "written_utc": "2026-07-19T01:17:08.649550+00:00"
}
