{
  "artifact": "phase5_5_trial_checkpoint_v1",
  "batch_id": "P5BAT-P5-DV-1.0.2-A7C91E42-phase5_adversarial_core-M2-MIX-MIX-BASELINE-4676675D-C302",
  "checkpoint_sequence": 9,
  "completed_lineage_count": 50,
  "last_attempt_id": "P5ATT-T01980-A000-4676675D",
  "last_target_trial_id": "T01980",
  "lineage_sha256": "ec97551c1c59d7ceaca168fd81e426f7c6b9fcb02cab9c1eabe86838383095c2",
  "model_slot": "M2",
  "parent_head": "9730156ecb0e62512941689aa6a848dc7b0485d9",
  "run_id": "P5RUN-P5-DV-1.0.2-A7C91E42-M2-20260718-0A3C9E18",
  "written_utc": "2026-07-18T20:10:10.761471+00:00"
}
